examples/envelope_minecart.py
examples/eupg_fishwood.py
examples/gpi_pd_hopper.py
examples/gpi_pd_minecart.py
examples/mo_q_learning_DST.py
examples/morld_cheetah.py
examples/morld_hopper.py
examples/morld_lunar_lander.py
examples/morld_lunar_lander_restore.py
examples/mp_mo_q_learning_DST.py
examples/ols_dst.py
examples/pcn_minecart.py
examples/pgmorl_halfcheetah.py
examples/pql_dst.py
morl_baselines/__init__.py
morl_baselines/common/__init__.py
morl_baselines/common/accrued_reward_buffer.py
morl_baselines/common/buffer.py
morl_baselines/common/diverse_buffer.py
morl_baselines/common/evaluation.py
morl_baselines/common/experiments.py
morl_baselines/common/morl_algorithm.py
morl_baselines/common/networks.py
morl_baselines/common/pareto.py
morl_baselines/common/performance_indicators.py
morl_baselines/common/prioritized_buffer.py
morl_baselines/common/scalarization.py
morl_baselines/common/utils.py
morl_baselines/common/weights.py
morl_baselines/common/model_based/__init__.py
morl_baselines/common/model_based/probabilistic_ensemble.py
morl_baselines/common/model_based/tabular_model.py
morl_baselines/common/model_based/utils.py
morl_baselines/multi_policy/__init__.py
morl_baselines/multi_policy/capql/__init__.py
morl_baselines/multi_policy/capql/capql.py
morl_baselines/multi_policy/envelope/__init__.py
morl_baselines/multi_policy/envelope/envelope.py
morl_baselines/multi_policy/gpi_pd/__init__.py
morl_baselines/multi_policy/gpi_pd/gpi_pd.py
morl_baselines/multi_policy/gpi_pd/gpi_pd_continuous_action.py
morl_baselines/multi_policy/linear_support/__init__.py
morl_baselines/multi_policy/linear_support/linear_support.py
morl_baselines/multi_policy/morld/__init__.py
morl_baselines/multi_policy/morld/morld.py
morl_baselines/multi_policy/multi_policy_moqlearning/__init__.py
morl_baselines/multi_policy/multi_policy_moqlearning/mp_mo_q_learning.py
morl_baselines/multi_policy/pareto_q_learning/__init__.py
morl_baselines/multi_policy/pareto_q_learning/pql.py
morl_baselines-1.2.0.dist-info/licenses/LICENSE
morl_baselines-1.2.0.dist-info/METADATA
morl_baselines-1.2.0.dist-info/WHEEL
morl_baselines-1.2.0.dist-info/top_level.txt
morl_baselines-1.2.0.dist-info/RECORD
