Metadata-Version: 2.4
Name: morl-baselines
Version: 1.2.0
Summary: Implementations of multi-objective reinforcement learning (MORL) algorithms.
Author-email: Florian Felten & Lucas Alegre <lucasnale@gmail.com>
License: MIT License
Project-URL: Homepage, https://lucasalegre.github.io/morl-baselines/
Project-URL: Repository, https://github.com/LucasAlegre/morl-baselines
Project-URL: Documentation, https://lucasalegre.github.io/morl-baselines/
Project-URL: Bug Report, https://github.com/LucasAlegre/morl-baselines/issues
Keywords: Reinforcement Learning,Multi-Objective,RL,AI,gymnasium
Classifier: Development Status :: 4 - Beta
Classifier: License :: OSI Approved :: MIT License
Classifier: Programming Language :: Python :: 3
Classifier: Programming Language :: Python :: 3.8
Classifier: Programming Language :: Python :: 3.9
Classifier: Programming Language :: Python :: 3.10
Classifier: Programming Language :: Python :: 3.11
Classifier: Programming Language :: Python :: 3.12
Classifier: Intended Audience :: Science/Research
Classifier: Topic :: Scientific/Engineering :: Artificial Intelligence
Requires-Python: >=3.8
License-File: LICENSE
Requires-Dist: mo-gymnasium>=1.3.0
Requires-Dist: gymnasium>=1.0.0
Requires-Dist: numpy<2.0.0,>=1.21.0
Requires-Dist: torch>=1.12.0
Requires-Dist: pygame>=2.1.0
Requires-Dist: scipy>=1.7.3
Requires-Dist: pymoo>=0.6.0
Requires-Dist: wandb>=0.14.0
Requires-Dist: imageio
Requires-Dist: moviepy
Requires-Dist: seaborn
Requires-Dist: cvxpy
Requires-Dist: fire
Provides-Extra: ols
Requires-Dist: pycddlib==2.1.6; extra == "ols"
Provides-Extra: gpi
Requires-Dist: pycddlib==2.1.6; extra == "gpi"
Provides-Extra: all
Requires-Dist: pycddlib==2.1.6; extra == "all"
Provides-Extra: testing
Requires-Dist: pytest==7.1.3; extra == "testing"
Dynamic: license-file
